[
{"rate": [], "num_participated": [], "country": []},
{"rate": ["\r\n        3686\r\n    "], "num_participated": ["\r\n        150\r\n    "], "country": ["Belarus"]},
{"rate": ["\r\n        3330\r\n    "], "num_participated": ["\r\n        129\r\n    "], "country": ["Russia"]},
{"rate": ["\r\n        3329\r\n    "], "num_participated": ["\r\n        97\r\n    "], "country": ["Samoa"]},
{"rate": ["\r\n        3296\r\n    "], "num_participated": ["\r\n        79\r\n    "], "country": ["Poland"]},
{"rate": ["\r\n        3294\r\n    "], "num_participated": ["\r\n        67\r\n    "], "country": ["United States"]},
{"rate": ["\r\n        3279\r\n    "], "num_participated": ["\r\n        36\r\n    "], "country": ["China"]},
{"rate": ["\r\n        3275\r\n    "], "num_participated": ["\r\n        123\r\n    "], "country": ["Russia"]},
{"rate": ["\r\n        3220\r\n    "], "num_participated": ["\r\n        68\r\n    "], "country": ["United States"]},
{"rate": ["\r\n        3190\r\n    "], "num_participated": ["\r\n        47\r\n    "], "country": ["Japan"]},
{"rate": ["\r\n        3147\r\n    "], "num_participated": ["\r\n        17\r\n    "], "country": ["China"]},
{"rate": ["\r\n        3120\r\n    "], "num_participated": ["\r\n        156\r\n    "], "country": ["South Korea"]},
{"rate": ["\r\n        3118\r\n    "], "num_participated": ["\r\n        19\r\n    "], "country": ["Japan"]},
{"rate": ["\r\n        3117\r\n    "], "num_participated": ["\r\n        126\r\n    "], "country": ["Poland"]},
{"rate": ["\r\n        3115\r\n    "], "num_participated": ["\r\n        143\r\n    "], "country": ["Russia"]},
{"rate": ["\r\n        3096\r\n    "], "num_participated": ["\r\n        82\r\n    "], "country": ["South Korea"]},
{"rate": ["\r\n        3056\r\n    "], "num_participated": ["\r\n        12\r\n    "], "country": ["China"]},
{"rate": ["\r\n        3055\r\n    "], "num_participated": ["\r\n        30\r\n    "], "country": ["China"]},
{"rate": ["\r\n        3023\r\n    "], "num_participated": ["\r\n        53\r\n    "], "country": ["China"]},
{"rate": ["\r\n        3020\r\n    "], "num_participated": ["\r\n        138\r\n    "], "country": ["Canada"]},
{"rate": ["\r\n        3020\r\n    "], "num_participated": ["\r\n        92\r\n    "], "country": ["Russia"]},
{"rate": ["\r\n        3006\r\n    "], "num_participated": ["\r\n        117\r\n    "], "country": ["Japan"]},
{"rate": ["\r\n        3005\r\n    "], "num_participated": ["\r\n        88\r\n    "], "country": ["United States"]},
{"rate": ["\r\n        3005\r\n    "], "num_participated": ["\r\n        63\r\n    "], "country": ["South Korea"]},
{"rate": ["\r\n        3005\r\n    "], "num_participated": ["\r\n        94\r\n    "], "country": ["Russia"]},
{"rate": ["\r\n        3001\r\n    "], "num_participated": ["\r\n        176\r\n    "], "country": []},
{"rate": ["\r\n        2996\r\n    "], "num_participated": ["\r\n        48\r\n    "], "country": ["China"]},
{"rate": ["\r\n        2973\r\n    "], "num_participated": ["\r\n        156\r\n    "], "country": ["Russia"]},
{"rate": ["\r\n        2964\r\n    "], "num_participated": ["\r\n        33\r\n    "], "country": ["Netherlands"]},
{"rate": ["\r\n        2963\r\n    "], "num_participated": ["\r\n        105\r\n    "], "country": ["Poland"]},
{"rate": ["\r\n        2963\r\n    "], "num_participated": ["\r\n        21\r\n    "], "country": ["China"]},
{"rate": ["\r\n        2945\r\n    "], "num_participated": ["\r\n        35\r\n    "], "country": ["China"]},
{"rate": ["\r\n        2935\r\n    "], "num_participated": ["\r\n        40\r\n    "], "country": ["China"]},
{"rate": ["\r\n        2923\r\n    "], "num_participated": ["\r\n        96\r\n    "], "country": ["Japan"]},
{"rate": ["\r\n        2919\r\n    "], "num_participated": ["\r\n        182\r\n    "], "country": ["Russia"]},
{"rate": ["\r\n        2910\r\n    "], "num_participated": ["\r\n        24\r\n    "], "country": ["South Korea"]},
{"rate": ["\r\n        2904\r\n    "], "num_participated": ["\r\n        58\r\n    "], "country": ["China"]},
{"rate": ["\r\n        2903\r\n    "], "num_participated": ["\r\n        41\r\n    "], "country": ["Russia"]},
{"rate": ["\r\n        2885\r\n    "], "num_participated": ["\r\n        53\r\n    "], "country": ["China"]},
{"rate": ["\r\n        2880\r\n    "], "num_participated": ["\r\n        180\r\n    "], "country": ["Russia"]},
{"rate": ["\r\n        2861\r\n    "], "num_participated": ["\r\n        63\r\n    "], "country": ["Russia"]},
{"rate": ["\r\n        2860\r\n    "], "num_participated": ["\r\n        210\r\n    "], "country": ["Germany"]},
{"rate": ["\r\n        2859\r\n    "], "num_participated": ["\r\n        109\r\n    "], "country": ["Poland"]},
{"rate": ["\r\n        2843\r\n    "], "num_participated": ["\r\n        108\r\n    "], "country": ["China"]},
{"rate": ["\r\n        2843\r\n    "], "num_participated": ["\r\n        95\r\n    "], "country": ["South Korea"]},
{"rate": ["\r\n        2836\r\n    "], "num_participated": ["\r\n        70\r\n    "], "country": ["United States"]},
{"rate": ["\r\n        2826\r\n    "], "num_participated": ["\r\n        149\r\n    "], "country": ["Iran"]},
{"rate": ["\r\n        2824\r\n    "], "num_participated": ["\r\n        228\r\n    "], "country": ["Ukraine"]},
{"rate": ["\r\n        2824\r\n    "], "num_participated": ["\r\n        126\r\n    "], "country": ["Russia"]},
{"rate": ["\r\n        2821\r\n    "], "num_participated": ["\r\n        35\r\n    "], "country": ["China"]},
{"rate": ["\r\n        2811\r\n    "], "num_participated": ["\r\n        106\r\n    "], "country": ["Japan"]},
{"rate": ["\r\n        2810\r\n    "], "num_participated": ["\r\n        164\r\n    "], "country": ["Russia"]},
{"rate": ["\r\n        2810\r\n    "], "num_participated": ["\r\n        22\r\n    "], "country": ["Taiwan"]},
{"rate": ["\r\n        2807\r\n    "], "num_participated": ["\r\n        120\r\n    "], "country": ["Latvia"]},
{"rate": ["\r\n        2800\r\n    "], "num_participated": ["\r\n        81\r\n    "], "country": ["Iran"]},
{"rate": ["\r\n        2798\r\n    "], "num_participated": ["\r\n        210\r\n    "], "country": ["Russia"]},
{"rate": ["\r\n        2796\r\n    "], "num_participated": ["\r\n        39\r\n    "], "country": ["Japan"]},
{"rate": ["\r\n        2795\r\n    "], "num_participated": ["\r\n        58\r\n    "], "country": []},
{"rate": ["\r\n        2792\r\n    "], "num_participated": ["\r\n        48\r\n    "], "country": ["Czechia"]},
{"rate": ["\r\n        2791\r\n    "], "num_participated": ["\r\n        146\r\n    "], "country": ["Russia"]},
{"rate": ["\r\n        2784\r\n    "], "num_participated": ["\r\n        87\r\n    "], "country": ["Poland"]},
{"rate": ["\r\n        2783\r\n    "], "num_participated": ["\r\n        170\r\n    "], "country": ["Russia"]},
{"rate": ["\r\n        2779\r\n    "], "num_participated": ["\r\n        52\r\n    "], "country": ["China"]},
{"rate": ["\r\n        2779\r\n    "], "num_participated": ["\r\n        81\r\n    "], "country": ["Russia"]},
{"rate": ["\r\n        2777\r\n    "], "num_participated": ["\r\n        20\r\n    "], "country": ["China"]},
{"rate": ["\r\n        2776\r\n    "], "num_participated": ["\r\n        83\r\n    "], "country": ["Japan"]},
{"rate": ["\r\n        2764\r\n    "], "num_participated": ["\r\n        59\r\n    "], "country": ["China"]},
{"rate": ["\r\n        2759\r\n    "], "num_participated": ["\r\n        145\r\n    "], "country": ["Poland"]},
{"rate": ["\r\n        2752\r\n    "], "num_participated": ["\r\n        259\r\n    "], "country": ["Japan"]},
{"rate": ["\r\n        2750\r\n    "], "num_participated": ["\r\n        56\r\n    "], "country": ["Russia"]},
{"rate": ["\r\n        2749\r\n    "], "num_participated": ["\r\n        78\r\n    "], "country": ["Japan"]},
{"rate": ["\r\n        2749\r\n    "], "num_participated": ["\r\n        72\r\n    "], "country": ["Finland"]},
{"rate": ["\r\n        2747\r\n    "], "num_participated": ["\r\n        33\r\n    "], "country": ["South Korea"]},
{"rate": ["\r\n        2746\r\n    "], "num_participated": ["\r\n        33\r\n    "], "country": ["China"]},
{"rate": ["\r\n        2744\r\n    "], "num_participated": ["\r\n        36\r\n    "], "country": ["North Korea"]},
{"rate": ["\r\n        2743\r\n    "], "num_participated": ["\r\n        13\r\n    "], "country": ["Taiwan"]},
{"rate": ["\r\n        2742\r\n    "], "num_participated": ["\r\n        99\r\n    "], "country": ["Japan"]},
{"rate": ["\r\n        2741\r\n    "], "num_participated": ["\r\n        131\r\n    "], "country": ["Poland"]},
{"rate": ["\r\n        2739\r\n    "], "num_participated": ["\r\n        121\r\n    "], "country": ["Ukraine"]},
{"rate": ["\r\n        2737\r\n    "], "num_participated": ["\r\n        137\r\n    "], "country": ["Switzerland"]},
{"rate": ["\r\n        2728\r\n    "], "num_participated": ["\r\n        60\r\n    "], "country": ["Russia"]},
{"rate": ["\r\n        2727\r\n    "], "num_participated": ["\r\n        23\r\n    "], "country": ["China"]},
{"rate": ["\r\n        2726\r\n    "], "num_participated": ["\r\n        116\r\n    "], "country": ["Russia"]},
{"rate": ["\r\n        2723\r\n    "], "num_participated": ["\r\n        115\r\n    "], "country": ["Canada"]},
{"rate": ["\r\n        2722\r\n    "], "num_participated": ["\r\n        7\r\n    "], "country": []},
{"rate": ["\r\n        2721\r\n    "], "num_participated": ["\r\n        117\r\n    "], "country": ["Russia"]},
{"rate": ["\r\n        2720\r\n    "], "num_participated": ["\r\n        111\r\n    "], "country": ["Taiwan"]},
{"rate": ["\r\n        2719\r\n    "], "num_participated": ["\r\n        143\r\n    "], "country": ["Hong Kong"]},
{"rate": ["\r\n        2716\r\n    "], "num_participated": ["\r\n        255\r\n    "], "country": ["Taiwan"]},
{"rate": ["\r\n        2716\r\n    "], "num_participated": ["\r\n        109\r\n    "], "country": ["Romania"]},
{"rate": ["\r\n        2714\r\n    "], "num_participated": ["\r\n        66\r\n    "], "country": ["Russia"]},
{"rate": ["\r\n        2710\r\n    "], "num_participated": ["\r\n        232\r\n    "], "country": ["Japan"]},
{"rate": ["\r\n        2709\r\n    "], "num_participated": ["\r\n        190\r\n    "], "country": ["Russia"]},
{"rate": ["\r\n        2706\r\n    "], "num_participated": ["\r\n        31\r\n    "], "country": ["China"]},
{"rate": ["\r\n        2705\r\n    "], "num_participated": ["\r\n        170\r\n    "], "country": ["Belarus"]},
{"rate": ["\r\n        2702\r\n    "], "num_participated": ["\r\n        32\r\n    "], "country": ["Sweden"]},
{"rate": ["\r\n        2700\r\n    "], "num_participated": ["\r\n        61\r\n    "], "country": ["South Korea"]},
{"rate": ["\r\n        2699\r\n    "], "num_participated": ["\r\n        25\r\n    "], "country": ["United States"]},
{"rate": ["\r\n        2699\r\n    "], "num_participated": ["\r\n        63\r\n    "], "country": ["Romania"]},
{"rate": ["\r\n        2694\r\n    "], "num_participated": ["\r\n        45\r\n    "], "country": ["South Korea"]},
{"rate": ["\r\n        2686\r\n    "], "num_participated": ["\r\n        61\r\n    "], "country": ["Indonesia"]},
{"rate": ["\r\n        2686\r\n    "], "num_participated": ["\r\n        43\r\n    "], "country": ["Argentina"]},
{"rate": ["\r\n        2684\r\n    "], "num_participated": ["\r\n        57\r\n    "], "country": ["China"]},
{"rate": ["\r\n        2684\r\n    "], "num_participated": ["\r\n        76\r\n    "], "country": ["China"]},
{"rate": ["\r\n        2683\r\n    "], "num_participated": ["\r\n        55\r\n    "], "country": ["China"]},
{"rate": ["\r\n        2675\r\n    "], "num_participated": ["\r\n        18\r\n    "], "country": ["Taiwan"]},
{"rate": ["\r\n        2673\r\n    "], "num_participated": ["\r\n        15\r\n    "], "country": []},
{"rate": ["\r\n        2670\r\n    "], "num_participated": ["\r\n        237\r\n    "], "country": ["Lithuania"]},
{"rate": ["\r\n        2665\r\n    "], "num_participated": ["\r\n        21\r\n    "], "country": ["China"]},
{"rate": ["\r\n        2664\r\n    "], "num_participated": ["\r\n        13\r\n    "], "country": ["China"]},
{"rate": ["\r\n        2664\r\n    "], "num_participated": ["\r\n        53\r\n    "], "country": ["Kazakhstan"]},
{"rate": ["\r\n        2661\r\n    "], "num_participated": ["\r\n        188\r\n    "], "country": ["Taiwan"]},
{"rate": ["\r\n        2654\r\n    "], "num_participated": ["\r\n        55\r\n    "], "country": ["Russia"]},
{"rate": ["\r\n        2654\r\n    "], "num_participated": ["\r\n        14\r\n    "], "country": ["China"]},
{"rate": ["\r\n        2654\r\n    "], "num_participated": ["\r\n        29\r\n    "], "country": ["Taiwan"]},
{"rate": ["\r\n        2649\r\n    "], "num_participated": ["\r\n        54\r\n    "], "country": ["China"]},
{"rate": ["\r\n        2642\r\n    "], "num_participated": ["\r\n        81\r\n    "], "country": ["Belarus"]},
{"rate": ["\r\n        2641\r\n    "], "num_participated": ["\r\n        78\r\n    "], "country": ["Japan"]},
{"rate": ["\r\n        2638\r\n    "], "num_participated": ["\r\n        188\r\n    "], "country": ["Russia"]},
{"rate": ["\r\n        2633\r\n    "], "num_participated": ["\r\n        77\r\n    "], "country": ["Lithuania"]},
{"rate": ["\r\n        2632\r\n    "], "num_participated": ["\r\n        30\r\n    "], "country": ["China"]},
{"rate": ["\r\n        2630\r\n    "], "num_participated": ["\r\n        147\r\n    "], "country": ["Russia"]},
{"rate": ["\r\n        2629\r\n    "], "num_participated": ["\r\n        53\r\n    "], "country": ["United States"]},
{"rate": ["\r\n        2628\r\n    "], "num_participated": ["\r\n        14\r\n    "], "country": ["China"]},
{"rate": ["\r\n        2626\r\n    "], "num_participated": ["\r\n        123\r\n    "], "country": ["South Korea"]},
{"rate": ["\r\n        2623\r\n    "], "num_participated": ["\r\n        52\r\n    "], "country": []},
{"rate": ["\r\n        2622\r\n    "], "num_participated": ["\r\n        123\r\n    "], "country": ["Vietnam"]},
{"rate": ["\r\n        2621\r\n    "], "num_participated": ["\r\n        24\r\n    "], "country": ["China"]},
{"rate": ["\r\n        2619\r\n    "], "num_participated": ["\r\n        13\r\n    "], "country": ["United States"]},
{"rate": ["\r\n        2618\r\n    "], "num_participated": ["\r\n        31\r\n    "], "country": ["China"]},
{"rate": ["\r\n        2614\r\n    "], "num_participated": ["\r\n        104\r\n    "], "country": ["Slovakia"]},
{"rate": ["\r\n        2614\r\n    "], "num_participated": ["\r\n        23\r\n    "], "country": ["North Korea"]},
{"rate": ["\r\n        2613\r\n    "], "num_participated": ["\r\n        43\r\n    "], "country": ["Hong Kong"]},
{"rate": ["\r\n        2612\r\n    "], "num_participated": ["\r\n        31\r\n    "], "country": ["Belgium"]},
{"rate": ["\r\n        2611\r\n    "], "num_participated": ["\r\n        87\r\n    "], "country": ["Japan"]},
{"rate": ["\r\n        2608\r\n    "], "num_participated": ["\r\n        86\r\n    "], "country": ["United States"]},
{"rate": ["\r\n        2603\r\n    "], "num_participated": ["\r\n        22\r\n    "], "country": ["China"]},
{"rate": ["\r\n        2603\r\n    "], "num_participated": ["\r\n        32\r\n    "], "country": []},
{"rate": ["\r\n        2599\r\n    "], "num_participated": ["\r\n        132\r\n    "], "country": ["Russia"]},
{"rate": ["\r\n        2599\r\n    "], "num_participated": ["\r\n        79\r\n    "], "country": ["China"]},
{"rate": ["\r\n        2597\r\n    "], "num_participated": ["\r\n        52\r\n    "], "country": ["China"]},
{"rate": ["\r\n        2594\r\n    "], "num_participated": ["\r\n        29\r\n    "], "country": ["China"]},
{"rate": ["\r\n        2593\r\n    "], "num_participated": ["\r\n        13\r\n    "], "country": ["South Korea"]},
{"rate": ["\r\n        2592\r\n    "], "num_participated": ["\r\n        27\r\n    "], "country": ["China"]},
{"rate": ["\r\n        2591\r\n    "], "num_participated": ["\r\n        41\r\n    "], "country": ["Canada"]},
{"rate": ["\r\n        2589\r\n    "], "num_participated": ["\r\n        206\r\n    "], "country": ["Japan"]},
{"rate": ["\r\n        2588\r\n    "], "num_participated": ["\r\n        9\r\n    "], "country": ["China"]},
{"rate": ["\r\n        2581\r\n    "], "num_participated": ["\r\n        16\r\n    "], "country": ["China"]},
{"rate": ["\r\n        2580\r\n    "], "num_participated": ["\r\n        60\r\n    "], "country": ["Russia"]},
{"rate": ["\r\n        2580\r\n    "], "num_participated": ["\r\n        122\r\n    "], "country": ["Russia"]},
{"rate": ["\r\n        2578\r\n    "], "num_participated": ["\r\n        40\r\n    "], "country": ["South Korea"]},
{"rate": ["\r\n        2575\r\n    "], "num_participated": ["\r\n        71\r\n    "], "country": ["United States"]},
{"rate": ["\r\n        2572\r\n    "], "num_participated": ["\r\n        107\r\n    "], "country": ["Iran"]},
{"rate": ["\r\n        2569\r\n    "], "num_participated": ["\r\n        45\r\n    "], "country": ["Russia"]},
{"rate": ["\r\n        2567\r\n    "], "num_participated": ["\r\n        81\r\n    "], "country": ["Japan"]},
{"rate": ["\r\n        2565\r\n    "], "num_participated": ["\r\n        80\r\n    "], "country": ["Canada"]},
{"rate": ["\r\n        2564\r\n    "], "num_participated": ["\r\n        39\r\n    "], "country": ["Russia"]},
{"rate": ["\r\n        2564\r\n    "], "num_participated": ["\r\n        12\r\n    "], "country": ["Vietnam"]},
{"rate": ["\r\n        2563\r\n    "], "num_participated": ["\r\n        200\r\n    "], "country": ["United States"]},
{"rate": ["\r\n        2563\r\n    "], "num_participated": ["\r\n        131\r\n    "], "country": ["Russia"]},
{"rate": ["\r\n        2563\r\n    "], "num_participated": ["\r\n        16\r\n    "], "country": ["China"]},
{"rate": ["\r\n        2563\r\n    "], "num_participated": ["\r\n        26\r\n    "], "country": ["Sweden"]},
{"rate": ["\r\n        2561\r\n    "], "num_participated": ["\r\n        12\r\n    "], "country": ["China"]},
{"rate": ["\r\n        2560\r\n    "], "num_participated": ["\r\n        33\r\n    "], "country": ["Russia"]},
{"rate": ["\r\n        2559\r\n    "], "num_participated": ["\r\n        62\r\n    "], "country": []},
{"rate": ["\r\n        2559\r\n    "], "num_participated": ["\r\n        66\r\n    "], "country": ["South Korea"]},
{"rate": ["\r\n        2557\r\n    "], "num_participated": ["\r\n        131\r\n    "], "country": ["Taiwan"]},
{"rate": ["\r\n        2554\r\n    "], "num_participated": ["\r\n        8\r\n    "], "country": ["China"]},
{"rate": ["\r\n        2553\r\n    "], "num_participated": ["\r\n        50\r\n    "], "country": ["Poland"]},
{"rate": ["\r\n        2553\r\n    "], "num_participated": ["\r\n        106\r\n    "], "country": ["Russia"]},
{"rate": ["\r\n        2551\r\n    "], "num_participated": ["\r\n        21\r\n    "], "country": ["Iran"]},
{"rate": ["\r\n        2550\r\n    "], "num_participated": ["\r\n        57\r\n    "], "country": ["Poland"]},
{"rate": ["\r\n        2549\r\n    "], "num_participated": ["\r\n        110\r\n    "], "country": []},
{"rate": ["\r\n        2549\r\n    "], "num_participated": ["\r\n        213\r\n    "], "country": ["Ukraine"]},
{"rate": ["\r\n        2549\r\n    "], "num_participated": ["\r\n        68\r\n    "], "country": ["Japan"]},
{"rate": ["\r\n        2547\r\n    "], "num_participated": ["\r\n        8\r\n    "], "country": []},
{"rate": ["\r\n        2545\r\n    "], "num_participated": ["\r\n        166\r\n    "], "country": ["Ukraine"]},
{"rate": ["\r\n        2542\r\n    "], "num_participated": ["\r\n        7\r\n    "], "country": ["China"]},
{"rate": ["\r\n        2540\r\n    "], "num_participated": ["\r\n        99\r\n    "], "country": ["Iran"]},
{"rate": ["\r\n        2539\r\n    "], "num_participated": ["\r\n        107\r\n    "], "country": ["Japan"]},
{"rate": ["\r\n        2539\r\n    "], "num_participated": ["\r\n        15\r\n    "], "country": ["Vietnam"]},
{"rate": ["\r\n        2538\r\n    "], "num_participated": ["\r\n        82\r\n    "], "country": ["United States"]},
{"rate": ["\r\n        2537\r\n    "], "num_participated": ["\r\n        17\r\n    "], "country": []},
{"rate": ["\r\n        2534\r\n    "], "num_participated": ["\r\n        85\r\n    "], "country": ["Iran"]},
{"rate": ["\r\n        2533\r\n    "], "num_participated": ["\r\n        14\r\n    "], "country": ["Iran"]},
{"rate": ["\r\n        2529\r\n    "], "num_participated": ["\r\n        17\r\n    "], "country": ["China"]},
{"rate": ["\r\n        2529\r\n    "], "num_participated": ["\r\n        38\r\n    "], "country": ["Poland"]},
{"rate": ["\r\n        2529\r\n    "], "num_participated": ["\r\n        5\r\n    "], "country": ["China"]},
{"rate": ["\r\n        2528\r\n    "], "num_participated": ["\r\n        36\r\n    "], "country": ["China"]},
{"rate": ["\r\n        2527\r\n    "], "num_participated": ["\r\n        23\r\n    "], "country": ["China"]},
{"rate": ["\r\n        2526\r\n    "], "num_participated": ["\r\n        33\r\n    "], "country": ["Russia"]},
{"rate": ["\r\n        2524\r\n    "], "num_participated": ["\r\n        49\r\n    "], "country": ["Belarus"]},
{"rate": ["\r\n        2523\r\n    "], "num_participated": ["\r\n        54\r\n    "], "country": ["Poland"]},
{"rate": ["\r\n        2523\r\n    "], "num_participated": ["\r\n        69\r\n    "], "country": ["Japan"]},
{"rate": ["\r\n        2521\r\n    "], "num_participated": ["\r\n        10\r\n    "], "country": ["China"]},
{"rate": ["\r\n        2518\r\n    "], "num_participated": ["\r\n        115\r\n    "], "country": ["France"]},
{"rate": ["\r\n        2518\r\n    "], "num_participated": ["\r\n        17\r\n    "], "country": ["Japan"]},
{"rate": ["\r\n        2515\r\n    "], "num_participated": ["\r\n        75\r\n    "], "country": ["Poland"]},
{"rate": ["\r\n        2515\r\n    "], "num_participated": ["\r\n        112\r\n    "], "country": ["India"]},
{"rate": ["\r\n        2515\r\n    "], "num_participated": ["\r\n        3\r\n    "], "country": ["China"]},
{"rate": ["\r\n        2514\r\n    "], "num_participated": ["\r\n        163\r\n    "], "country": ["Ukraine"]}
]